Workbook

Sheet README
A1: Mortality Table Builder: actuarial workbook
A2: Mexico's life tables with live commutation functions. Source: github.com/deadmigue55/Mortality-Table-Builder
A4: How to use
A5: 1. Open the Calculator sheet. Blue cells are inputs: table, issue age, interest rate, term, sum assured.
A6: 2. Table_M, Table_F and Table_CNSF hold qx and the formulas for lx, dx, Dx, Nx, Cx and Mx. Click any cell to audit it.
A7: 3. Change the interest rate and every commutation column, premium and annuity moves with it.
A8: 4. Rate_Card, Excess_Mortality, Annuity_Stress and Table_Comparison hold results of the full pipeline as values.
A10: What the numbers are
A11: Tables: INEGI registered deaths and CONAPO population, completed for late registration and graduated (P-spline), year 2023.
A12: CNSF 2013: the regulatory mortality table in force (mixed-sex). Net premiums here are mortality and interest only.
A13: Rate_Card and Annuity_Stress use illustrative expense, commission and lapse assumptions and a synthetic book: methods, not a quote.
A15: Audit
A16: This workbook is recomputed by an independent formula engine in the project's tests and compared with the Python functions.

Sheet Calculator
A1: Actuarial calculator
A2: Blue cells are inputs. Everything else is a live formula on the Table_ sheets. | D2: Tables
A3: Mortality table | B3: Mexico 2023, men | D3: Mexico 2023, men
A4: Issue age x | B4: 40 | D4: Mexico 2023, women
A5: Interest rate i | B5: 0.04 | D5: CNSF 2013 (regulatory)
A6: Term n (years) | B6: 20
A7: Sum assured (MXN) | B7: 1000000
A9: Table number (helper) | B9: =MATCH(B3, D3:D5, 0)
A10: Position of age x (helper) | B10: =B4+1
A11: Position of age x + n (helper) | B11: =MIN(B4+B6,110)+1
A12: Results
A13: Curtate life expectancy e(x), years | B13: =CHOOSE($B$9, SUMIF(Table_M!$A$2:$A$112, ">"&$B$4, Table_M!$C$2:$C$112), SUMIF(Table_F!$A$2:$A$112, ">"&$B$4, Table_F!$C$2:$C$112), SUMIF(Table_CNSF!$A$2:$A$112, ">"&$B$4, Table_CNSF!$C$2:$C$112))/(CHOOSE($B$9, INDEX(Table_M!$C$2:$C$112, $B$10), INDEX(Table_F!$C$2:$C$112, $B$10), INDEX(Table_CNSF!$C$2:$C$112, $B$10)))
A14: Whole-life insurance A(x), per unit | B14: =(CHOOSE($B$9, INDEX(Table_M!$H$2:$H$112, $B$10), INDEX(Table_F!$H$2:$H$112, $B$10), INDEX(Table_CNSF!$H$2:$H$112, $B$10)))/(CHOOSE($B$9, INDEX(Table_M!$E$2:$E$112, $B$10), INDEX(Table_F!$E$2:$E$112, $B$10), INDEX(Table_CNSF!$E$2:$E$112, $B$10)))
A15: Life annuity-due a(x), per unit a year | B15: =(CHOOSE($B$9, INDEX(Table_M!$F$2:$F$112, $B$10), INDEX(Table_F!$F$2:$F$112, $B$10), INDEX(Table_CNSF!$F$2:$F$112, $B$10)))/(CHOOSE($B$9, INDEX(Table_M!$E$2:$E$112, $B$10), INDEX(Table_F!$E$2:$E$112, $B$10), INDEX(Table_CNSF!$E$2:$E$112, $B$10)))
A16: Term insurance A(x:n), per unit | B16: =((CHOOSE($B$9, INDEX(Table_M!$H$2:$H$112, $B$10), INDEX(Table_F!$H$2:$H$112, $B$10), INDEX(Table_CNSF!$H$2:$H$112, $B$10)))-(CHOOSE($B$9, INDEX(Table_M!$H$2:$H$112, $B$11), INDEX(Table_F!$H$2:$H$112, $B$11), INDEX(Table_CNSF!$H$2:$H$112, $B$11))))/(CHOOSE($B$9, INDEX(Table_M!$E$2:$E$112, $B$10), INDEX(Table_F!$E$2:$E$112, $B$10), INDEX(Table_CNSF!$E$2:$E$112, $B$10)))
A17: Temporary annuity-due a(x:n) | B17: =((CHOOSE($B$9, INDEX(Table_M!$F$2:$F$112, $B$10), INDEX(Table_F!$F$2:$F$112, $B$10), INDEX(Table_CNSF!$F$2:$F$112, $B$10)))-(CHOOSE($B$9, INDEX(Table_M!$F$2:$F$112, $B$11), INDEX(Table_F!$F$2:$F$112, $B$11), INDEX(Table_CNSF!$F$2:$F$112, $B$11))))/(CHOOSE($B$9, INDEX(Table_M!$E$2:$E$112, $B$10), INDEX(Table_F!$E$2:$E$112, $B$10), INDEX(Table_CNSF!$E$2:$E$112, $B$10)))
A18: Net annual premium rate, per unit of sum assured | B18: =B16/B17
A19: Net annual premium, MXN | B19: =B18*B7
A20: Net premium per 1,000 of sum assured | B20: =B18*1000
A21: Annuity of 100,000 a year for life, MXN | B21: =B15*100000
A23: Net premiums only (mortality and interest, no expenses or profit): the gross premium from the profit test on the Rate_Card sheet adds acquisition cost, commission, maintenance and a target return.

Sheet Table_M
A1: Age x | B1: qx | C1: lx | D1: dx | E1: Dx | F1: Nx | G1: Cx | H1: Mx | J1: Mexico 2023, men
A2: 0 | B2: 0.010417296 | C2: 100000 | D2: =C2*B2 | E2: =C2*(1/(1+Calculator!$B$5))^A2 | F2: =SUM(E2:E$112) | G2: =D2*(1/(1+Calculator!$B$5))^(A2+1) | H2: =SUM(G2:G$112) | J2: Edit the interest rate on the Calculator sheet.
A3: 1 | B3: 0.00092062862 | C3: =C2*(1-B2) | D3: =C3*B3 | E3: =C3*(1/(1+Calculator!$B$5))^A3 | F3: =SUM(E3:E$112) | G3: =D3*(1/(1+Calculator!$B$5))^(A3+1) | H3: =SUM(G3:G$112)
A4: 2 | B4: 0.00056766823 | C4: =C3*(1-B3) | D4: =C4*B4 | E4: =C4*(1/(1+Calculator!$B$5))^A4 | F4: =SUM(E4:E$112) | G4: =D4*(1/(1+Calculator!$B$5))^(A4+1) | H4: =SUM(G4:G$112)
A5: 3 | B5: 0.00039000311 | C5: =C4*(1-B4) | D5: =C5*B5 | E5: =C5*(1/(1+Calculator!$B$5))^A5 | F5: =SUM(E5:E$112) | G5: =D5*(1/(1+Calculator!$B$5))^(A5+1) | H5: =SUM(G5:G$112)
A6: 4 | B6: 0.00030824961 | C6: =C5*(1-B5) | D6: =C6*B6 | E6: =C6*(1/(1+Calculator!$B$5))^A6 | F6: =SUM(E6:E$112) | G6: =D6*(1/(1+Calculator!$B$5))^(A6+1) | H6: =SUM(G6:G$112)
A7: 5 | B7: 0.0002732772 | C7: =C6*(1-B6) | D7: =C7*B7 | E7: =C7*(1/(1+Calculator!$B$5))^A7 | F7: =SUM(E7:E$112) | G7: =D7*(1/(1+Calculator!$B$5))^(A7+1) | H7: =SUM(G7:G$112)
A8: 6 | B8: 0.00025850019 | C8: =C7*(1-B7) | D8: =C8*B8 | E8: =C8*(1/(1+Calculator!$B$5))^A8 | F8: =SUM(E8:E$112) | G8: =D8*(1/(1+Calculator!$B$5))^(A8+1) | H8: =SUM(G8:G$112)
A9: 7 | B9: 0.00025196824 | C9: =C8*(1-B8) | D9: =C9*B9 | E9: =C9*(1/(1+Calculator!$B$5))^A9 | F9: =SUM(E9:E$112) | G9: =D9*(1/(1+Calculator!$B$5))^(A9+1) | H9: =SUM(G9:G$112)
A10: 8 | B10: 0.0002474344 | C10: =C9*(1-B9) | D10: =C10*B10 | E10: =C10*(1/(1+Calculator!$B$5))^A10 | F10: =SUM(E10:E$112) | G10: =D10*(1/(1+Calculator!$B$5))^(A10+1) | H10: =SUM(G10:G$112)
A11: 9 | B11: 0.00024424227 | C11: =C10*(1-B10) | D11: =C11*B11 | E11: =C11*(1/(1+Calculator!$B$5))^A11 | F11: =SUM(E11:E$112) | G11: =D11*(1/(1+Calculator!$B$5))^(A11+1) | H11: =SUM(G11:G$112)
A12: 10 | B12: 0.00024815486 | C12: =C11*(1-B11) | D12: =C12*B12 | E12: =C12*(1/(1+Calculator!$B$5))^A12 | F12: =SUM(E12:E$112) | G12: =D12*(1/(1+Calculator!$B$5))^(A12+1) | H12: =SUM(G12:G$112)
A13: 11 | B13: 0.00026577486 | C13: =C12*(1-B12) | D13: =C13*B13 | E13: =C13*(1/(1+Calculator!$B$5))^A13 | F13: =SUM(E13:E$112) | G13: =D13*(1/(1+Calculator!$B$5))^(A13+1) | H13: =SUM(G13:G$112)
A14: 12 | B14: 0.00030618112 | C14: =C13*(1-B13) | D14: =C14*B14 | E14: =C14*(1/(1+Calculator!$B$5))^A14 | F14: =SUM(E14:E$112) | G14: =D14*(1/(1+Calculator!$B$5))^(A14+1) | H14: =SUM(G14:G$112)
... A112: 110 | B112: 1 | C112: =C111*(1-B111) | D112: =C112*B112 | E112: =C112*(1/(1+Calculator!$B$5))^A112 | F112: =SUM(E112:E$112) | G112: =D112*(1/(1+Calculator!$B$5))^(A112+1) | H112: =SUM(G112:G$112)

Sheet Table_F
A1: Age x | B1: qx | C1: lx | D1: dx | E1: Dx | F1: Nx | G1: Cx | H1: Mx | J1: Mexico 2023, women
A2: 0 | B2: 0.0083754219 | C2: 100000 | D2: =C2*B2 | E2: =C2*(1/(1+Calculator!$B$5))^A2 | F2: =SUM(E2:E$112) | G2: =D2*(1/(1+Calculator!$B$5))^(A2+1) | H2: =SUM(G2:G$112) | J2: Edit the interest rate on the Calculator sheet.
A3: 1 | B3: 0.00079572866 | C3: =C2*(1-B2) | D3: =C3*B3 | E3: =C3*(1/(1+Calculator!$B$5))^A3 | F3: =SUM(E3:E$112) | G3: =D3*(1/(1+Calculator!$B$5))^(A3+1) | H3: =SUM(G3:G$112)
A4: 2 | B4: 0.00050546596 | C4: =C3*(1-B3) | D4: =C4*B4 | E4: =C4*(1/(1+Calculator!$B$5))^A4 | F4: =SUM(E4:E$112) | G4: =D4*(1/(1+Calculator!$B$5))^(A4+1) | H4: =SUM(G4:G$112)
A5: 3 | B5: 0.00034995313 | C5: =C4*(1-B4) | D5: =C5*B5 | E5: =C5*(1/(1+Calculator!$B$5))^A5 | F5: =SUM(E5:E$112) | G5: =D5*(1/(1+Calculator!$B$5))^(A5+1) | H5: =SUM(G5:G$112)
A6: 4 | B6: 0.00027127305 | C6: =C5*(1-B5) | D6: =C6*B6 | E6: =C6*(1/(1+Calculator!$B$5))^A6 | F6: =SUM(E6:E$112) | G6: =D6*(1/(1+Calculator!$B$5))^(A6+1) | H6: =SUM(G6:G$112)
A7: 5 | B7: 0.0002322776 | C7: =C6*(1-B6) | D7: =C7*B7 | E7: =C7*(1/(1+Calculator!$B$5))^A7 | F7: =SUM(E7:E$112) | G7: =D7*(1/(1+Calculator!$B$5))^(A7+1) | H7: =SUM(G7:G$112)
A8: 6 | B8: 0.0002129269 | C8: =C7*(1-B7) | D8: =C8*B8 | E8: =C8*(1/(1+Calculator!$B$5))^A8 | F8: =SUM(E8:E$112) | G8: =D8*(1/(1+Calculator!$B$5))^(A8+1) | H8: =SUM(G8:G$112)
A9: 7 | B9: 0.00020368189 | C9: =C8*(1-B8) | D9: =C9*B9 | E9: =C9*(1/(1+Calculator!$B$5))^A9 | F9: =SUM(E9:E$112) | G9: =D9*(1/(1+Calculator!$B$5))^(A9+1) | H9: =SUM(G9:G$112)
A10: 8 | B10: 0.00019912701 | C10: =C9*(1-B9) | D10: =C10*B10 | E10: =C10*(1/(1+Calculator!$B$5))^A10 | F10: =SUM(E10:E$112) | G10: =D10*(1/(1+Calculator!$B$5))^(A10+1) | H10: =SUM(G10:G$112)
A11: 9 | B11: 0.00019769001 | C11: =C10*(1-B10) | D11: =C11*B11 | E11: =C11*(1/(1+Calculator!$B$5))^A11 | F11: =SUM(E11:E$112) | G11: =D11*(1/(1+Calculator!$B$5))^(A11+1) | H11: =SUM(G11:G$112)
A12: 10 | B12: 0.00020174613 | C12: =C11*(1-B11) | D12: =C12*B12 | E12: =C12*(1/(1+Calculator!$B$5))^A12 | F12: =SUM(E12:E$112) | G12: =D12*(1/(1+Calculator!$B$5))^(A12+1) | H12: =SUM(G12:G$112)
A13: 11 | B13: 0.00021402223 | C13: =C12*(1-B12) | D13: =C13*B13 | E13: =C13*(1/(1+Calculator!$B$5))^A13 | F13: =SUM(E13:E$112) | G13: =D13*(1/(1+Calculator!$B$5))^(A13+1) | H13: =SUM(G13:G$112)
A14: 12 | B14: 0.00023750233 | C14: =C13*(1-B13) | D14: =C14*B14 | E14: =C14*(1/(1+Calculator!$B$5))^A14 | F14: =SUM(E14:E$112) | G14: =D14*(1/(1+Calculator!$B$5))^(A14+1) | H14: =SUM(G14:G$112)
... A112: 110 | B112: 1 | C112: =C111*(1-B111) | D112: =C112*B112 | E112: =C112*(1/(1+Calculator!$B$5))^A112 | F112: =SUM(E112:E$112) | G112: =D112*(1/(1+Calculator!$B$5))^(A112+1) | H112: =SUM(G112:G$112)

Sheet Table_CNSF
A1: Age x | B1: qx | C1: lx | D1: dx | E1: Dx | F1: Nx | G1: Cx | H1: Mx | J1: CNSF 2013 (regulatory)
A2: 0 | B2: 0.000433 | C2: 100000 | D2: =C2*B2 | E2: =C2*(1/(1+Calculator!$B$5))^A2 | F2: =SUM(E2:E$112) | G2: =D2*(1/(1+Calculator!$B$5))^(A2+1) | H2: =SUM(G2:G$112) | J2: Edit the interest rate on the Calculator sheet.
A3: 1 | B3: 0.000433 | C3: =C2*(1-B2) | D3: =C3*B3 | E3: =C3*(1/(1+Calculator!$B$5))^A3 | F3: =SUM(E3:E$112) | G3: =D3*(1/(1+Calculator!$B$5))^(A3+1) | H3: =SUM(G3:G$112)
A4: 2 | B4: 0.000434 | C4: =C3*(1-B3) | D4: =C4*B4 | E4: =C4*(1/(1+Calculator!$B$5))^A4 | F4: =SUM(E4:E$112) | G4: =D4*(1/(1+Calculator!$B$5))^(A4+1) | H4: =SUM(G4:G$112)
A5: 3 | B5: 0.000434 | C5: =C4*(1-B4) | D5: =C5*B5 | E5: =C5*(1/(1+Calculator!$B$5))^A5 | F5: =SUM(E5:E$112) | G5: =D5*(1/(1+Calculator!$B$5))^(A5+1) | H5: =SUM(G5:G$112)
A6: 4 | B6: 0.000435 | C6: =C5*(1-B5) | D6: =C6*B6 | E6: =C6*(1/(1+Calculator!$B$5))^A6 | F6: =SUM(E6:E$112) | G6: =D6*(1/(1+Calculator!$B$5))^(A6+1) | H6: =SUM(G6:G$112)
A7: 5 | B7: 0.000436 | C7: =C6*(1-B6) | D7: =C7*B7 | E7: =C7*(1/(1+Calculator!$B$5))^A7 | F7: =SUM(E7:E$112) | G7: =D7*(1/(1+Calculator!$B$5))^(A7+1) | H7: =SUM(G7:G$112)
A8: 6 | B8: 0.000438 | C8: =C7*(1-B7) | D8: =C8*B8 | E8: =C8*(1/(1+Calculator!$B$5))^A8 | F8: =SUM(E8:E$112) | G8: =D8*(1/(1+Calculator!$B$5))^(A8+1) | H8: =SUM(G8:G$112)
A9: 7 | B9: 0.00044 | C9: =C8*(1-B8) | D9: =C9*B9 | E9: =C9*(1/(1+Calculator!$B$5))^A9 | F9: =SUM(E9:E$112) | G9: =D9*(1/(1+Calculator!$B$5))^(A9+1) | H9: =SUM(G9:G$112)
A10: 8 | B10: 0.000443 | C10: =C9*(1-B9) | D10: =C10*B10 | E10: =C10*(1/(1+Calculator!$B$5))^A10 | F10: =SUM(E10:E$112) | G10: =D10*(1/(1+Calculator!$B$5))^(A10+1) | H10: =SUM(G10:G$112)
A11: 9 | B11: 0.000446 | C11: =C10*(1-B10) | D11: =C11*B11 | E11: =C11*(1/(1+Calculator!$B$5))^A11 | F11: =SUM(E11:E$112) | G11: =D11*(1/(1+Calculator!$B$5))^(A11+1) | H11: =SUM(G11:G$112)
A12: 10 | B12: 0.000449 | C12: =C11*(1-B11) | D12: =C12*B12 | E12: =C12*(1/(1+Calculator!$B$5))^A12 | F12: =SUM(E12:E$112) | G12: =D12*(1/(1+Calculator!$B$5))^(A12+1) | H12: =SUM(G12:G$112)
A13: 11 | B13: 0.000453 | C13: =C12*(1-B12) | D13: =C13*B13 | E13: =C13*(1/(1+Calculator!$B$5))^A13 | F13: =SUM(E13:E$112) | G13: =D13*(1/(1+Calculator!$B$5))^(A13+1) | H13: =SUM(G13:G$112)
A14: 12 | B14: 0.000457 | C14: =C13*(1-B13) | D14: =C14*B14 | E14: =C14*(1/(1+Calculator!$B$5))^A14 | F14: =SUM(E14:E$112) | G14: =D14*(1/(1+Calculator!$B$5))^(A14+1) | H14: =SUM(G14:G$112)
... A112: 110 | B112: 1 | C112: =C111*(1-B111) | D112: =C112*B112 | E112: =C112*(1/(1+Calculator!$B$5))^A112 | F112: =SUM(E112:E$112) | G112: =D112*(1/(1+Calculator!$B$5))^(A112+1) | H112: =SUM(G112:G$112)

Sheet Rate_Card
A1: Gross premium of a level term policy, sum assured 1,000,000, solved for a 10% return on CNSF 2013 (illustrative expenses and lapses).
A3: Sex | B3: Issue age | C3: Term | D3: Net per 1000 | E3: Gross per 1000 | F3: Gross premium MXN | G3: Loading over net | H3: IRR | I3: Year-1 profit | J3: Payback year
A4: F | B4: 25 | C4: 10 | D4: 0.64111879 | E4: 1.2568202 | F4: 1256.8202 | G4: 0.96035466 | H4: 0.1 | I4: -1220.8972 | J4: 0
A5: F | B5: 30 | C5: 10 | D5: 0.77304291 | E5: 1.4105849 | F5: 1410.5849 | G5: 0.82471741 | H5: 0.1 | I5: -1313.347 | J5: 0
A6: F | B6: 35 | C6: 10 | D6: 0.96924973 | E6: 1.6391029 | F6: 1639.1029 | G6: 0.69110482 | H6: 0.1 | I6: -1450.9145 | J6: 0
A7: F | B7: 40 | C7: 10 | D7: 1.2656009 | E7: 1.9836046 | F7: 1983.6046 | G7: 0.56732234 | H7: 0.1 | I7: -1658.4235 | J7: 0
A8: F | B8: 45 | C8: 10 | D8: 1.7237163 | E8: 2.5148576 | F8: 2514.8576 | G8: 0.45897421 | H8: 0.1 | I8: -1978.6812 | J8: 10
A9: F | B9: 50 | C9: 10 | D9: 2.4515874 | E9: 3.3568208 | F9: 3356.8208 | G9: 0.36924374 | H9: 0.1 | I9: -2486.5759 | J9: 10
A10: F | B10: 55 | C10: 10 | D10: 3.6442708 | E10: 4.7328356 | F10: 4732.8356 | G10: 0.2987058 | H10: 0.1 | I10: -3317.0702 | J10: 10
A11: F | B11: 60 | C11: 10 | D11: 5.6643745 | E11: 7.0583336 | F11: 7058.3336 | G11: 0.24609233 | H11: 0.1 | I11: -4720.3814 | J11: 0
A12: F | B12: 25 | C12: 20 | D12: 0.77278662 | E12: 1.3320515 | F12: 1332.0515 | G12: 0.72369896 | H12: 0.1 | I12: -1323.0208 | J12: 18
A13: F | B13: 30 | C13: 20 | D13: 0.9704508 | E13: 1.535125 | F13: 1535.125 | G13: 0.58186795 | H13: 0.1 | I13: -1463.3759 | J13: 19
A14: F | B14: 35 | C14: 20 | D14: 1.2710718 | E14: 1.8422582 | F14: 1842.2582 | G14: 0.44937381 | H14: 0.1 | I14: -1676.9528 | J14: 19
A15: F | B15: 40 | C15: 20 | D15: 1.7387036 | E15: 2.3164119 | F15: 2316.4119 | G15: 0.33226381 | H15: 0.1 | I15: -2008.9654 | J15: 19
... A35: M | B35: 60 | C35: 20 | D35: 9.4375007 | E35: 9.9254629 | F35: 9925.4629 | G35: 0.051704599 | H35: 0.1 | I35: -7460.1656 | J35: 19

Sheet Excess_Mortality
A1: Observed against expected deaths, both sexes; the central estimate is the median of four baselines.
A3: Year | B3: Observed | C3: Expected | D3: Excess deaths | E3: Low | F3: High | G3: P-score | H3: Certified COVID-19
A4: 2020 | B4: 1093072.9 | C4: 760624.57 | D4: 332448.34 | E4: 319970.04 | F4: 339894.01 | G4: 0.43707285 | H4: 201280
A5: 2021 | B5: 1117649.9 | C5: 766871.45 | D5: 350778.45 | E5: 327669.33 | F5: 365700.08 | G5: 0.45741494 | H5: 238093
A6: 2022 | B6: 843756.81 | C6: 780554.24 | D6: 63202.572 | E6: 28294.764 | F6: 85731.666 | G6: 0.080971403 | H6: 38189
A7: 2023 | B7: 798055.28 | C7: 802108.98 | D7: -4053.7025 | E7: -51585.04 | F7: 26370.741 | G7: -0.0050538052 | H7: 4625
A8: 2024 | B8: 814221.16 | C8: 824304.75 | D8: -10083.589 | E8: -71058.504 | F8: 28524.318 | G8: -0.012232841 | H8: 1353

Sheet Annuity_Stress
A1: Reserve of an illustrative block of 20,000 pensioners (synthetic) on each mortality basis, annuity-due at 4%.
A3: Basis | B3: Reserve men | C3: Reserve women | D3: Reserve total | E3: Against central
A4: CNSF 2013, pensions variant | B4: 1.7391118e+10 | C4: 1.1594079e+10 | D4: 2.8985197e+10 | E4: 0.15977681
A5: CNSF 2013 | B5: 1.6159397e+10 | C5: 1.0772932e+10 | D5: 2.6932329e+10 | E5: 0.077635964
A6: Mexican population 2023 (no improvement) | B6: 1.4299064e+10 | C6: 9.9560759e+09 | D6: 2.425514e+10 | E6: -0.029485688
A7: Projection with no improvement after 2025 | B7: 1.4406512e+10 | C7: 1.0030693e+10 | D7: 2.4437205e+10 | E7: -0.022200766
A8: Central projection (step 7) | B8: 1.4731562e+10 | C8: 1.0260485e+10 | D8: 2.4992047e+10 | E8: 0
A9: Projection with double the improvement | B9: 1.5068611e+10 | C9: 1.049706e+10 | D9: 2.5565671e+10 | E9: 0.022952251
A10: Central, mortality 20% lower for good | B10: 1.5655675e+10 | C10: 1.0823279e+10 | D10: 2.6478954e+10 | E10: 0.059495188
A11: Central, interest 1 point lower | B11: 1.591414e+10 | C11: 1.1114549e+10 | D11: 2.7028689e+10 | E11: 0.081491579
A12: Central, interest 1 point higher | B12: 1.3708693e+10 | C12: 9.5239948e+09 | D12: 2.3232688e+10 | E12: -0.070396758

Sheet Table_Comparison
A1: Mexican population tables against regulatory and SOA tables, at 4%.
A3: Source | B3: Table | C3: Sex | D3: e0 | E3: e65 | F3: Annuity at 65 | G3: A(40) | H3: 20-year term premium at 40
A4: CNSF | B4: CNSF M 2013 (non-disabled lives, base) | C4: T | D4: 84.421149 | E4: 22.808611 | F4: 14.939446 | G4: 0.18312867 | H4: 0.0017387036
A5: CNSF | B5: CNSF M 2013 (p0.05 percentile) | C5: T | D5: 88.308409 | E5: 25.743429 | F5: 16.098656 | G5: 0.15929385 | H5: 0.0011557669
A6: CNSF | B6: CNSF M 2013 (p99.5 percentile) | C6: T | D6: 80.249231 | E6: 19.923549 | F6: 13.682875 | G6: 0.21114167 | H6: 0.0026150229
A7: HMD | B7: CAN 2019 | C7: F | D7: 84.355216 | E7: 22.397227 | F7: 14.735088 | G7: 0.18629143 | H7: 0.0017154039
A8: HMD | B8: CAN 2019 | C8: M | D8: 80.119739 | E8: 19.642748 | F8: 13.491544 | G8: 0.21616166 | H8: 0.0027369229
A9: HMD | B9: CAN 2019 | C9: T | D9: 82.252301 | E9: 21.089044 | F9: 14.139647 | G9: 0.20103152 | H9: 0.0022234068
A10: HMD | B10: CHL 2019 | C10: F | D10: 83.314592 | E10: 21.751831 | F10: 14.402095 | G10: 0.19345934 | H10: 0.001905494
A11: HMD | B11: CHL 2019 | C11: M | D11: 77.748642 | E11: 18.458683 | F11: 12.869358 | G11: 0.23479087 | H11: 0.0036372939
A12: HMD | B12: CHL 2019 | C12: T | D12: 80.611178 | E12: 20.250295 | F12: 13.69857 | G12: 0.213299 | H12: 0.0027394353
A13: HMD | B13: ESP 2019 | C13: F | D13: 86.16004 | E13: 23.343091 | F13: 15.236866 | G13: 0.17400141 | H13: 0.0013161682
A14: HMD | B14: ESP 2019 | C14: M | D14: 80.72548 | E14: 19.375659 | F14: 13.370863 | G14: 0.21615093 | H14: 0.002535342
A15: HMD | B15: ESP 2019 | C15: T | D15: 83.489914 | E15: 21.476209 | F15: 14.354396 | G15: 0.19473106 | H15: 0.0019243618
... A36: INEGI/CONAPO | B36: Mexico, graduated 2023 | C36: T | D36: 75.878261 | E36: 18.295134 | F36: 12.733256 | G36: 0.24921219 | H36: 0.0048332072
A37: SOA | B37: CNSF 2000-G group life (1991-1998) | C37: T | E37: 14.504123 | F37: 10.986125 | G37: 0.27091583 | H37: 0.0047566059
A38: SOA | B38: CNSF 2000-I individual insured lives (1991-1998) | C38: T | E38: 17.69661 | F38: 12.349662 | G38: 0.26686696 | H38: 0.0060167935
A39: SOA | B39: EMSSA 97 pension participants (H) | C39: M | E39: 16.487228 | F39: 11.931099 | G39: 0.25681157 | H39: 0.0045769028
A40: SOA | B40: EMSSA 97 pension participants (M) | C40: F | E40: 19.869967 | F40: 13.533063 | G40: 0.21127737 | H40: 0.0023426316
A41: SOA | B41: Experiencia Mexicana individual (1982-1989) | C41: T | E41: 15.550373 | F41: 11.383792 | G41: 0.28117398 | H41: 0.0062537582
A42: SOA | B42: MEX 2000 female | C42: F | D42: 78.475196 | E42: 18.148824 | F42: 12.815237 | G42: 0.22744095 | H42: 0.0030079171
A43: SOA | B43: MEX 2000 male | C43: M | D43: 74.768332 | E43: 16.007949 | F43: 11.681244 | G43: 0.25699069 | H43: 0.0039004022
A44: SOA | B44: Seguro Popular 2008 females | C44: F | E44: 16.441411 | F44: 11.918607 | G44: 0.25689344 | H44: 0.0044926232
A45: SOA | B45: Seguro Popular 2008 males | C45: M | E45: 14.566514 | F45: 10.88301 | G45: 0.31566623 | H45: 0.0094843498
